pyflick/__init__.py
pyflick/authentication.py
pyflick/const.py
pyflick/types.py
PyFlick-1.1.3.dist-info/LICENSE.txt
PyFlick-1.1.3.dist-info/METADATA
PyFlick-1.1.3.dist-info/WHEEL
PyFlick-1.1.3.dist-info/top_level.txt
PyFlick-1.1.3.dist-info/RECORD
