Metadata-Version: 2.2
Name: PyFlick
Version: 1.1.3
Summary: Python API For Flick Electric in New Zealand
Author-email: ZephireNZ <brynley+pypi@zephire.nz>
License: The MIT License (MIT)
Project-URL: Homepage, https://github.com/ZephireNZ/PyFlick
Classifier: License :: OSI Approved :: MIT License
Classifier: Operating System :: OS Independent
Classifier: Programming Language :: Python :: 3
Requires-Python: >=3.6
License-File: LICENSE.txt
Requires-Dist: aiohttp>=3.11.10
Requires-Dist: json-api-doc>=0.15.0
Requires-Dist: python-dateutil>=2.9.0.post0
